Workbook

Sheet valor_apurado
A1: meta | B1: =IF(B3="data",CONCATENATE(procv!B1,"_",procv!B3),IF(valor_apurado!B3="valor",CONCATENATE(procv!B1,"_",procv!B3),IF(valor_apurado!B3="informacao",CONCATENATE(procv!B1,"_",procv!B2),"Erro"))) -> TJMG 7 -_Apurado no período | C1: =IF(C3="data",CONCATENATE(procv!C1,"_",procv!C3),IF(valor_apurado!C3="valor",CONCATENATE(procv!C1,"_",procv!C3),IF(valor_apurado!C3="informacao",CONCATENATE(procv!C1,"_",procv!C2),"Erro"))) -> TJMG 7 -_Apurado no período | D1: =IF(D3="data",CONCATENATE(procv!D1,"_",procv!D3),IF(valor_apurado!D3="valor",CONCATENATE(procv!D1,"_",procv!D3),IF(valor_apurado!D3="informacao",CONCATENATE(procv!D1,"_",procv!D2),"Erro"))) -> TJMG 7 -_12 | E1: =IF(E3="data",CONCATENATE(procv!E1,"_",procv!E3),IF(valor_apurado!E3="valor",CONCATENATE(procv!E1,"_",procv!E3),IF(valor_apurado!E3="informacao",CONCATENATE(procv!E1,"_",procv!E2),"Erro"))) -> TJMG 10 _Apurado no período | F1: =IF(F3="data",CONCATENATE(procv!F1,"_",procv!F3),IF(valor_apurado!F3="valor",CONCATENATE(procv!F1,"_",procv!F3),IF(valor_apurado!F3="informacao",CONCATENATE(procv!F1,"_",procv!F2),"Erro"))) -> TJMG 10 _Apurado no período | G1: =IF(G3="data",CONCATENATE(procv!G1,"_",procv!G3),IF(valor_apurado!G3="valor",CONCATENATE(procv!G1,"_",procv!G3),IF(valor_apurado!G3="informacao",CONCATENATE(procv!G1,"_",procv!G2),"Erro"))) -> TJMG 10 _12 | H1: =IF(H3="data",CONCATENATE(procv!H1,"_",procv!H3),IF(valor_apurado!H3="valor",CONCATENATE(procv!H1,"_",procv!H3),IF(valor_apurado!H3="informacao",CONCATENATE(procv!H1,"_",procv!H2),"Erro"))) -> TJMG 100_Apurado no período | I1: =IF(I3="data",CONCATENATE(procv!I1,"_",procv!I3),IF(valor_apurado!I3="valor",CONCATENATE(procv!I1,"_",procv!I3),IF(valor_apurado!I3="informacao",CONCATENATE(procv!I1,"_",procv!I2),"Erro"))) -> TJMG 100_Apurado no período | J1: =IF(J3="data",CONCATENATE(procv!J1,"_",procv!J3),IF(valor_apurado!J3="valor",CONCATENATE(procv!J1,"_",procv!J3),IF(valor_apurado!J3="informacao",CONCATENATE(procv!J1,"_",procv!J2),"Erro"))) -> TJMG 100_12 | K1: =IF(K3="data",CONCATENATE(procv!N1,"_",procv!N3),IF(valor_apurado!K3="valor",CONCATENATE(procv!N1,"_",procv!N3),IF(valor_apurado!K3="informacao",CONCATENATE(procv!N1,"_",procv!N2),"Erro"))) -> TJMG 104_Apurado no período | L1: =IF(L3="data",CONCATENATE(procv!O1,"_",procv!O3),IF(valor_apurado!L3="valor",CONCATENATE(procv!O1,"_",procv!O3),IF(valor_apurado!L3="informacao",CONCATENATE(procv!O1,"_",procv!O2),"Erro"))) -> TJMG 104_Apurado no período | M1: =IF(M3="data",CONCATENATE(procv!P1,"_",procv!P3),IF(valor_apurado!M3="valor",CONCATENATE(procv!P1,"_",procv!P3),IF(valor_apurado!M3="informacao",CONCATENATE(procv!P1,"_",procv!P2),"Erro"))) -> TJMG 104_12 | N1: =IF(N3="data",CONCATENATE(procv!AC1,"_",procv!AC3),IF(valor_apurado!N3="valor",CONCATENATE(procv!AC1,"_",procv!AC3),IF(valor_apurado!N3="informacao",CONCATENATE(procv!AC1,"_",procv!AC2),"Erro"))) -> TJMG 109_Apurado no período | O1: =IF(O3="data",CONCATENATE(procv!AD1,"_",procv!AD3),IF(valor_apurado!O3="valor",CONCATENATE(procv!AD1,"_",procv!AD3),IF(valor_apurado!O3="informacao",CONCATENATE(procv!AD1,"_",procv!AD2),"Erro"))) -> TJMG 109_Apurado no período | P1: =IF(P3="data",CONCATENATE(procv!AE1,"_",procv!AE3),IF(valor_apurado!P3="valor",CONCATENATE(procv!AE1,"_",procv!AE3),IF(valor_apurado!P3="informacao",CONCATENATE(procv!AE1,"_",procv!AE2),"Erro"))) -> TJMG 109_12 | Q1: =IF(Q3="data",CONCATENATE(procv!AL1,"_",procv!AL3),IF(valor_apurado!Q3="valor",CONCATENATE(procv!AL1,"_",procv!AL3),IF(valor_apurado!Q3="informacao",CONCATENATE(procv!AL1,"_",procv!AL2),"Erro"))) -> TJMG 111_Apurado no período | R1: =IF(R3="data",CONCATENATE(procv!AM1,"_",procv!AM3),IF(valor_apurado!R3="valor",CONCATENATE(procv!AM1,"_",procv!AM3),IF(valor_apurado!R3="informacao",CONCATENATE(procv!AM1,"_",procv!AM2),"Erro"))) -> TJMG 111_Apurado no período | S1: =IF(S3="data",CONCATENATE(procv!AN1,"_",procv!AN3),IF(valor_apurado!S3="valor",CONCATENATE(procv!AN1,"_",procv!AN3),IF(valor_apurado!S3="informacao",CONCATENATE(procv!AN1,"_",procv!AN2),"Erro"))) -> TJMG 111_12 | T1: =IF(T3="data",CONCATENATE(procv!AX1,"_",procv!AX3),IF(valor_apurado!T3="valor",CONCATENATE(procv!AX1,"_",procv!AX3),IF(valor_apurado!T3="informacao",CONCATENATE(procv!AX1,"_",procv!AX2),"Erro"))) -> TJMG 115_Apurado no período | U1: =IF(U3="data",CONCATENATE(procv!AY1,"_",procv!AY3),IF(valor_apurado!U3="valor",CONCATENATE(procv!AY1,"_",procv!AY3),IF(valor_apurado!U3="informacao",CONCATENATE(procv!AY1,"_",procv!AY2),"Erro"))) -> TJMG 115_Apurado no período | V1: =IF(V3="data",CONCATENATE(procv!AZ1,"_",procv!AZ3),IF(valor_apurado!V3="valor",CONCATENATE(procv!AZ1,"_",procv!AZ3),IF(valor_apurado!V3="informacao",CONCATENATE(procv!AZ1,"_",procv!AZ2),"Erro"))) -> TJMG 115_12 | W1: =IF(W3="data",CONCATENATE(procv!BY1,"_",procv!BY3),IF(valor_apurado!W3="valor",CONCATENATE(procv!BY1,"_",procv!BY3),IF(valor_apurado!W3="informacao",CONCATENATE(procv!BY1,"_",procv!BY2),"Erro"))) -> TJMG 123_Apurado no período | X1: =IF(X3="data",CONCATENATE(procv!BZ1,"_",procv!BZ3),IF(valor_apurado!X3="valor",CONCATENATE(procv!BZ1,"_",procv!BZ3),IF(valor_apurado!X3="informacao",CONCATENATE(procv!BZ1,"_",procv!BZ2),"Erro"))) -> TJMG 123_Apurado no período | Y1: =IF(Y3="data",CONCATENATE(procv!CA1,"_",procv!CA3),IF(valor_apurado!Y3="valor",CONCATENATE(procv!CA1,"_",procv!CA3),IF(valor_apurado!Y3="informacao",CONCATENATE(procv!CA1,"_",procv!CA2),"Erro"))) -> TJMG 123_12 | Z1: =IF(Z3="data",CONCATENATE(procv!CB1,"_",procv!CB3),IF(valor_apurado!Z3="valor",CONCATENATE(procv!CB1,"_",procv!CB3),IF(valor_apurado!Z3="informacao",CONCATENATE(procv!CB1,"_",procv!CB2),"Erro"))) -> TJMG 124_Apurado no período | AA1: =IF(AA3="data",CONCATENATE(procv!CC1,"_",procv!CC3),IF(valor_apurado!AA3="valor",CONCATENATE(procv!CC1,"_",procv!CC3),IF(valor_apurado!AA3="informacao",CONCATENATE(procv!CC1,"_",procv!CC2),"Erro"))) -> TJMG 124_Apurado no período | AB1: =IF(AB3="data",CONCATENATE(procv!CD1,"_",procv!CD3),IF(valor_apurado!AB3="valor",CONCATENATE(procv!CD1,"_",procv!CD3),IF(valor_apurado!AB3="informacao",CONCATENATE(procv!CD1,"_",procv!CD2),"Erro"))) -> TJMG 124_12 | AC1: =IF(AC3="data",CONCATENATE(procv!CH1,"_",procv!CH3),IF(valor_apurado!AC3="valor",CONCATENATE(procv!CH1,"_",procv!CH3),IF(valor_apurado!AC3="informacao",CONCATENATE(procv!CH1,"_",procv!CH2),"Erro"))) -> TJMG 126_Apurado no período | AD1: =IF(AD3="data",CONCATENATE(procv!CI1,"_",procv!CI3),IF(valor_apurado!AD3="valor",CONCATENATE(procv!CI1,"_",procv!CI3),IF(valor_apurado!AD3="informacao",CONCATENATE(procv!CI1,"_",procv!CI2),"Erro"))) -> TJMG 126_Apurado no período | AE1: =IF(AE3="data",CONCATENATE(procv!CJ1,"_",procv!CJ3),IF(valor_apurado!AE3="valor",CONCATENATE(procv!CJ1,"_",procv!CJ3),IF(valor_apurado!AE3="informacao",CONCATENATE(procv!CJ1,"_",procv!CJ2),"Erro"))) -> TJMG 126_12 | AF1: =IF(AF3="data",CONCATENATE(procv!CQ1,"_",procv!CQ3),IF(valor_apurado!AF3="valor",CONCATENATE(procv!CQ1,"_",procv!CQ3),IF(valor_apurado!AF3="informacao",CONCATENATE(procv!CQ1,"_",procv!CQ2),"Erro"))) -> TJMG 17 _Apurado no período | AG1: =IF(AG3="data",CONCATENATE(procv!CR1,"_",procv!CR3),IF(valor_apurado!AG3="valor",CONCATENATE(procv!CR1,"_",procv!CR3),IF(valor_apurado!AG3="informacao",CONCATENATE(procv!CR1,"_",procv!CR2),"Erro"))) -> TJMG 17 _Apurado no período | AH1: =IF(AH3="data",CONCATENATE(procv!CS1,"_",procv!CS3),IF(valor_apurado!AH3="valor",CONCATENATE(procv!CS1,"_",procv!CS3),IF(valor_apurado!AH3="informacao",CONCATENATE(procv!CS1,"_",procv!CS2),"Erro"))) -> TJMG 17 _12 | AI1: =IF(AI3="data",CONCATENATE(procv!DL1,"_",procv!DL3),IF(valor_apurado!AI3="valor",CONCATENATE(procv!DL1,"_",procv!DL3),IF(valor_apurado!AI3="informacao",CONCATENATE(procv!DL1,"_",procv!DL2),"Erro"))) -> TJMG 29 _Apurado no período | AJ1: =IF(AJ3="data",CONCATENATE(procv!DM1,"_",procv!DM3),IF(valor_apurado!AJ3="valor",CONCATENATE(procv!DM1,"_",procv!DM3),IF(valor_apurado!AJ3="informacao",CONCATENATE(procv!DM1,"_",procv!DM2),"Erro"))) -> TJMG 29 _Apurado no período | AK1: =IF(AK3="data",CONCATENATE(procv!DN1,"_",procv!DN3),IF(valor_apurado!AK3="valor",CONCATENATE(procv!DN1,"_",procv!DN3),IF(valor_apurado!AK3="informacao",CONCATENATE(procv!DN1,"_",procv!DN2),"Erro"))) -> TJMG 29 _12 | AL1: =IF(AL3="data",CONCATENATE(procv!DU1,"_",procv!DU3),IF(valor_apurado!AL3="valor",CONCATENATE(procv!DU1,"_",procv!DU3),IF(valor_apurado!AL3="informacao",CONCATENATE(procv!DU1,"_",procv!DU2),"Erro"))) -> TJMG 40 _Apurado no período | AM1: =IF(AM3="data",CONCATENATE(procv!DV1,"_",procv!DV3),IF(valor_apurado!AM3="valor",CONCATENATE(procv!DV1,"_",procv!DV3),IF(valor_apurado!AM3="informacao",CONCATENATE(procv!DV1,"_",procv!DV2),"Erro"))) -> TJMG 40 _Apurado no período | AN1: =IF(AN3="data",CONCATENATE(procv!DW1,"_",procv!DW3),IF(valor_apurado!AN3="valor",CONCATENATE(procv!DW1,"_",procv!DW3),IF(valor_apurado!AN3="informacao",CONCATENATE(procv!DW1,"_",procv!DW2),"Erro"))) -> TJMG 40 _12 | AO1: =IF(AO3="data",CONCATENATE(procv!EJ1,"_",procv!EJ3),IF(valor_apurado!AO3="valor",CONCATENATE(procv!EJ1,"_",procv!EJ3),IF(valor_apurado!AO3="informacao",CONCATENATE(procv!EJ1,"_",procv!EJ2),"Erro"))) -> TJMG 5 -_Apurado no período | AP1: =IF(AP3="data",CONCATENATE(procv!EK1,"_",procv!EK3),IF(valor_apurado!AP3="valor",CONCATENATE(procv!EK1,"_",procv!EK3),IF(valor_apurado!AP3="informacao",CONCATENATE(procv!EK1,"_",procv!EK2),"Erro"))) -> TJMG 5 -_Apurado no período | AQ1: =IF(AQ3="data",CONCATENATE(procv!EL1,"_",procv!EL3),IF(valor_apurado!AQ3="valor",CONCATENATE(procv!EL1,"_",procv!EL3),IF(valor_apurado!AQ3="informacao",CONCATENATE(procv!EL1,"_",procv!EL2),"Erro"))) -> TJMG 5 -_12 | AR1: =IF(AR3="data",CONCATENATE(procv!EP1,"_",procv!EP3),IF(valor_apurado!AR3="valor",CONCATENATE(procv!EP1,"_",procv!EP3),IF(valor_apurado!AR3="informacao",CONCATENATE(procv!EP1,"_",procv!EP2),"Erro"))) -> TJMG 59 _Apurado no período | AS1: =IF(AS3="data",CONCATENATE(procv!EQ1,"_",procv!EQ3),IF(valor_apurado!AS3="valor",CONCATENATE(procv!EQ1,"_",procv!EQ3),IF(valor_apurado!AS3="informacao",CONCATENATE(procv!EQ1,"_",procv!EQ2),"Erro"))) -> TJMG 59 _Apurado no período | AT1: =IF(AT3="data",CONCATENATE(procv!ER1,"_",procv!ER3),IF(valor_apurado!AT3="valor",CONCATENATE(procv!ER1,"_",procv!ER3),IF(valor_apurado!AT3="informacao",CONCATENATE(procv!ER1,"_",procv!ER2),"Erro"))) -> TJMG 59 _12 | AU1: =IF(AU3="data",CONCATENATE(procv!ES1,"_",procv!ES3),IF(valor_apurado!AU3="valor",CONCATENATE(procv!ES1,"_",procv!ES3),IF(valor_apurado!AU3="informacao",CONCATENATE(procv!ES1,"_",procv!ES2),"Erro"))) -> TJMG 6 -_Apurado no período | AV1: =IF(AV3="data",CONCATENATE(procv!ET1,"_",procv!ET3),IF(valor_apurado!AV3="valor",CONCATENATE(procv!ET1,"_",procv!ET3),IF(valor_apurado!AV3="informacao",CONCATENATE(procv!ET1,"_",procv!ET2),"Erro"))) -> TJMG 6 -_Apurado no período | AW1: =IF(AW3="data",CONCATENATE(procv!EU1,"_",procv!EU3),IF(valor_apurado!AW3="valor",CONCATENATE(procv!EU1,"_",procv!EU3),IF(valor_apurado!AW3="informacao",CONCATENATE(procv!EU1,"_",procv!EU2),"Erro"))) -> TJMG 6 -_12 | AX1: =IF(AX3="data",CONCATENATE(procv!EV1,"_",procv!EV3),IF(valor_apurado!AX3="valor",CONCATENATE(procv!EV1,"_",procv!EV3),IF(valor_apurado!AX3="informacao",CONCATENATE(procv!EV1,"_",procv!EV2),"Erro"))) -> TJMG 62 _Apurado no período | AY1: =IF(AY3="data",CONCATENATE(procv!EW1,"_",procv!EW3),IF(valor_apurado!AY3="valor",CONCATENATE(procv!EW1,"_",procv!EW3),IF(valor_apurado!AY3="informacao",CONCATENATE(procv!EW1,"_",procv!EW2),"Erro"))) -> TJMG 62 _Apurado no período | AZ1: =IF(AZ3="data",CONCATENATE(procv!EX1,"_",procv!EX3),IF(valor_apurado!AZ3="valor",CONCATENATE(procv!EX1,"_",procv!EX3),IF(valor_apurado!AZ3="informacao",CONCATENATE(procv!EX1,"_",procv!EX2),"Erro"))) -> TJMG 62 _12 | BA1: =IF(BA3="data",CONCATENATE(procv!FE1,"_",procv!FE3),IF(valor_apurado!BA3="valor",CONCATENATE(procv!FE1,"_",procv!FE3),IF(valor_apurado!BA3="informacao",CONCATENATE(procv!FE1,"_",procv!FE2),"Erro"))) -> TJMG 67 _Apurado no período | BB1: =IF(BB3="data",CONCATENATE(procv!FF1,"_",procv!FF3),IF(valor_apurado!BB3="valor",CONCATENATE(procv!FF1,"_",procv!FF3),IF(valor_apurado!BB3="informacao",CONCATENATE(procv!FF1,"_",procv!FF2),"Erro"))) -> TJMG 67 _Apurado no período | BC1: =IF(BC3="data",CONCATENATE(procv!FG1,"_",procv!FG3),IF(valor_apurado!BC3="valor",CONCATENATE(procv!FG1,"_",procv!FG3),IF(valor_apurado!BC3="informacao",CONCATENATE(procv!FG1,"_",procv!FG2),"Erro"))) -> TJMG 67 _12 | BD1: =IF(BD3="data",CONCATENATE(procv!FK1,"_",procv!FK3),IF(valor_apurado!BD3="valor",CONCATENATE(procv!FK1,"_",procv!FK3),IF(valor_apurado!BD3="informacao",CONCATENATE(procv!FK1,"_",procv!FK2),"Erro"))) -> TJMG 69 _Apurado no período | BE1: =IF(BE3="data",CONCATENATE(procv!FL1,"_",procv!FL3),IF(valor_apurado!BE3="valor",CONCATENATE(procv!FL1,"_",procv!FL3),IF(valor_apurado!BE3="informacao",CONCATENATE(procv!FL1,"_",procv!FL2),"Erro"))) -> TJMG 69 _Apurado no período | BF1: =IF(BF3="data",CONCATENATE(procv!FM1,"_",procv!FM3),IF(valor_apurado!BF3="valor",CONCATENATE(procv!FM1,"_",procv!FM3),IF(valor_apurado!BF3="informacao",CONCATENATE(procv!FM1,"_",procv!FM2),"Erro"))) -> TJMG 69 _12 | BG1: =IF(BG3="data",CONCATENATE(procv!FW1,"_",procv!FW3),IF(valor_apurado!BG3="valor",CONCATENATE(procv!FW1,"_",procv!FW3),IF(valor_apurado!BG3="informacao",CONCATENATE(procv!FW1,"_",procv!FW2),"Erro"))) -> TJMG 79 _Apurado no período | BH1: =IF(BH3="data",CONCATENATE(procv!FX1,"_",procv!FX3),IF(valor_apurado!BH3="valor",CONCATENATE(procv!FX1,"_",procv!FX3),IF(valor_apurado!BH3="informacao",CONCATENATE(procv!FX1,"_",procv!FX2),"Erro"))) -> TJMG 79 _Apurado no período | BI1: =IF(BI3="data",CONCATENATE(procv!FY1,"_",procv!FY3),IF(valor_apurado!BI3="valor",CONCATENATE(procv!FY1,"_",procv!FY3),IF(valor_apurado!BI3="informacao",CONCATENATE(procv!FY1,"_",procv!FY2),"Erro"))) -> TJMG 79 _12 | BJ1: =IF(BJ3="data",CONCATENATE(procv!GC1,"_",procv!GC3),IF(valor_apurado!BJ3="valor",CONCATENATE(procv!GC1,"_",procv!GC3),IF(valor_apurado!BJ3="informacao",CONCATENATE(procv!GC1,"_",procv!GC2),"Erro"))) -> TJMG 80 _Apurado no período | BK1: =IF(BK3="data",CONCATENATE(procv!GD1,"_",procv!GD3),IF(valor_apurado!BK3="valor",CONCATENATE(procv!GD1,"_",procv!GD3),IF(valor_apurado!BK3="informacao",CONCATENATE(procv!GD1,"_",procv!GD2),"Erro"))) -> TJMG 80 _Apurado no período | BL1: =IF(BL3="data",CONCATENATE(procv!GE1,"_",procv!GE3),IF(valor_apurado!BL3="valor",CONCATENATE(procv!GE1,"_",procv!GE3),IF(valor_apurado!BL3="informacao",CONCATENATE(procv!GE1,"_",procv!GE2),"Erro"))) -> TJMG 80 _12 | BM1: =IF(BM3="data",CONCATENATE(procv!GI1,"_",procv!GI3),IF(valor_apurado!BM3="valor",CONCATENATE(procv!GI1,"_",procv!GI3),IF(valor_apurado!BM3="informacao",CONCATENATE(procv!GI1,"_",procv!GI2),"Erro"))) -> TJMG 85 _Apurado no período | BN1: =IF(BN3="data",CONCATENATE(procv!GJ1,"_",procv!GJ3),IF(valor_apurado!BN3="valor",CONCATENATE(procv!GJ1,"_",procv!GJ3),IF(valor_apurado!BN3="informacao",CONCATENATE(procv!GJ1,"_",procv!GJ2),"Erro"))) -> TJMG 85 _Apurado no período | BO1: =IF(BO3="data",CONCATENATE(procv!GK1,"_",procv!GK3),IF(valor_apurado!BO3="valor",CONCATENATE(procv!GK1,"_",procv!GK3),IF(valor_apurado!BO3="informacao",CONCATENATE(procv!GK1,"_",procv!GK2),"Erro"))) -> TJMG 85 _12 | BP1: =IF(BP3="data",CONCATENATE(procv!HA1,"_",procv!HA3),IF(valor_apurado!BP3="valor",CONCATENATE(procv!HA1,"_",procv!HA3),IF(valor_apurado!BP3="informacao",CONCATENATE(procv!HA1,"_",procv!HA2),"Erro"))) -> TJMG 91 _Apurado no período | BQ1: =IF(BQ3="data",CONCATENATE(procv!HB1,"_",procv!HB3),IF(valor_apurado!BQ3="valor",CONCATENATE(procv!HB1,"_",procv!HB3),IF(valor_apurado!BQ3="informacao",CONCATENATE(procv!HB1,"_",procv!HB2),"Erro"))) -> TJMG 91 _Apurado no período | BR1: =IF(BR3="data",CONCATENATE(procv!HC1,"_",procv!HC3),IF(valor_apurado!BR3="valor",CONCATENATE(procv!HC1,"_",procv!HC3),IF(valor_apurado!BR3="informacao",CONCATENATE(procv!HC1,"_",procv!HC2),"Erro"))) -> TJMG 91 _12 | BS1: =IF(BS3="data",CONCATENATE(procv!HJ1,"_",procv!HJ3),IF(valor_apurado!BS3="valor",CONCATENATE(procv!HJ1,"_",procv!HJ3),IF(valor_apurado!BS3="informacao",CONCATENATE(procv!HJ1,"_",procv!HJ2),"Erro"))) -> TJMG 95 _Apurado no período | BT1: =IF(BT3="data",CONCATENATE(procv!HK1,"_",procv!HK3),IF(valor_apurado!BT3="valor",CONCATENATE(procv!HK1,"_",procv!HK3),IF(valor_apurado!BT3="informacao",CONCATENATE(procv!HK1,"_",procv!HK2),"Erro"))) -> TJMG 95 _Apurado no período | BU1: =IF(BU3="data",CONCATENATE(procv!HL1,"_",procv!HL3),IF(valor_apurado!BU3="valor",CONCATENATE(procv!HL1,"_",procv!HL3),IF(valor_apurado!BU3="informacao",CONCATENATE(procv!HL1,"_",procv!HL2),"Erro"))) -> TJMG 95 _12 | BV1: =IF(BV3="data",CONCATENATE(procv!HM1,"_",procv!HM3),IF(valor_apurado!BV3="valor",CONCATENATE(procv!HM1,"_",procv!HM3),IF(valor_apurado!BV3="informacao",CONCATENATE(procv!HM1,"_",procv!HM2),"Erro"))) -> TJMG 96 _Apurado no período | BW1: =IF(BW3="data",CONCATENATE(procv!HN1,"_",procv!HN3),IF(valor_apurado!BW3="valor",CONCATENATE(procv!HN1,"_",procv!HN3),IF(valor_apurado!BW3="informacao",CONCATENATE(procv!HN1,"_",procv!HN2),"Erro"))) -> TJMG 96 _Apurado no período | BX1: =IF(BX3="data",CONCATENATE(procv!HO1,"_",procv!HO3),IF(valor_apurado!BX3="valor",CONCATENATE(procv!HO1,"_",procv!HO3),IF(valor_apurado!BX3="informacao",CONCATENATE(procv!HO1,"_",procv!HO2),"Erro"))) -> TJMG 96 _12 | BY1: =IF(BY3="data",CONCATENATE(procv!HP1,"_",procv!HP3),IF(valor_apurado!BY3="valor",CONCATENATE(procv!HP1,"_",procv!HP3),IF(valor_apurado!BY3="informacao",CONCATENATE(procv!HP1,"_",procv!HP2),"Erro"))) -> TJMG 97 _Apurado no período | BZ1: =IF(BZ3="data",CONCATENATE(procv!HQ1,"_",procv!HQ3),IF(valor_apurado!BZ3="valor",CONCATENATE(procv!HQ1,"_",procv!HQ3),IF(valor_apurado!BZ3="informacao",CONCATENATE(procv!HQ1,"_",procv!HQ2),"Erro"))) -> TJMG 97 _Apurado no período | CA1: =IF(CA3="data",CONCATENATE(procv!HR1,"_",procv!HR3),IF(valor_apurado!CA3="valor",CONCATENATE(procv!HR1,"_",procv!HR3),IF(valor_apurado!CA3="informacao",CONCATENATE(procv!HR1,"_",procv!HR2),"Erro"))) -> TJMG 97 _12 | CB1: =IF(CB3="data",CONCATENATE(procv!HY1,"_",procv!HY3),IF(valor_apurado!CB3="valor",CONCATENATE(procv!HY1,"_",procv!HY3),IF(valor_apurado!CB3="informacao",CONCATENATE(procv!HY1,"_",procv!HY2),"Erro"))) -> TJMG 128_Apurado no período | CC1: =IF(CC3="data",CONCATENATE(procv!HZ1,"_",procv!HZ3),IF(valor_apurado!CC3="valor",CONCATENATE(procv!HZ1,"_",procv!HZ3),IF(valor_apurado!CC3="informacao",CONCATENATE(procv!HZ1,"_",procv!HZ2),"Erro"))) -> TJMG 128_Apurado no período | CD1: =IF(CD3="data",CONCATENATE(procv!IA1,"_",procv!IA3),IF(valor_apurado!CD3="valor",CONCATENATE(procv!IA1,"_",procv!IA3),IF(valor_apurado!CD3="informacao",CONCATENATE(procv!IA1,"_",procv!IA2),"Erro"))) -> TJMG 128_12 | CE1: =IF(CE3="data",CONCATENATE(procv!IB1,"_",procv!IB3),IF(valor_apurado!CE3="valor",CONCATENATE(procv!IB1,"_",procv!IB3),IF(valor_apurado!CE3="informacao",CONCATENATE(procv!IB1,"_",procv!IB2),"Erro"))) -> TJMG 129_Apurado no período | CF1: =IF(CF3="data",CONCATENATE(procv!IC1,"_",procv!IC3),IF(valor_apurado!CF3="valor",CONCATENATE(procv!IC1,"_",procv!IC3),IF(valor_apurado!CF3="informacao",CONCATENATE(procv!IC1,"_",procv!IC2),"Erro"))) -> TJMG 129_Apurado no período | CG1: =IF(CG3="data",CONCATENATE(procv!ID1,"_",procv!ID3),IF(valor_apurado!CG3="valor",CONCATENATE(procv!ID1,"_",procv!ID3),IF(valor_apurado!CG3="informacao",CONCATENATE(procv!ID1,"_",procv!ID2),"Erro"))) -> TJMG 129_12 | CH1: =IF(CH3="data",CONCATENATE(procv!IE1,"_",procv!IE3),IF(valor_apurado!CH3="valor",CONCATENATE(procv!IE1,"_",procv!IE3),IF(valor_apurado!CH3="informacao",CONCATENATE(procv!IE1,"_",procv!IE2),"Erro"))) -> TJMG 130_Apurado no período | CI1: =IF(CI3="data",CONCATENATE(procv!IF1,"_",procv!IF3),IF(valor_apurado!CI3="valor",CONCATENATE(procv!IF1,"_",procv!IF3),IF(valor_apurado!CI3="informacao",CONCATENATE(procv!IF1,"_",procv!IF2),"Erro"))) -> TJMG 130_Apurado no período | ... EO1: =IF(EO3="data",CONCATENATE(procv!KL1,"_",procv!KL3),IF(valor_apurado!EO3="valor",CONCATENATE(procv!KL1,"_",procv!KL3),IF(valor_apurado!EO3="informacao",CONCATENATE(procv!KL1,"_",procv!KL2),"Erro"))) -> TJMG 149_12
A2: valor_apurado | B2: =IF(B3="data",_xlfn.XLOOKUP(B1,[1]bd_mala_direta!$A$1:$A$3048,[1]bd_mala_direta!$D$1:$D$3048,"-",0,-1),IF(B3="valor",_xlfn.XLOOKUP(B1,[1]bd_mala_direta!$A$1:$A$3048,[1]bd_mala_direta!$E$1:$E$3048,"-",0,-1),IF(B3="informacao",_xlfn.XLOOKUP(B1,[1]bd_mala_direta!$A$1:$A$3048,[1]bd_mala_direta!$G$1:$G$3048,"-",0,-1),"Erro"))) -> 45902 | C2: =IF(C3="data",_xlfn.XLOOKUP(C1,[1]bd_mala_direta!$A$1:$A$3048,[1]bd_mala_direta!$D$1:$D$3048,"-",0,-1),IF(C3="valor",_xlfn.XLOOKUP(C1,[1]bd_mala_direta!$A$1:$A$3048,[1]bd_mala_direta!$E$1:$E$3048,"-",0,-1),IF(C3="informacao",_xlfn.XLOOKUP(C1,[1]bd_mala_direta!$A$1:$A$3048,[1]bd_mala_direta!$G$1:$G$3048,"-",0,-1),"Erro"))) -> 92 | D2: =IF(D3="data",_xlfn.XLOOKUP(D1,[1]bd_mala_direta!$A$1:$A$3048,[1]bd_mala_direta!$D$1:$D$3048,"-",0,-1),IF(D3="valor",_xlfn.XLOOKUP(D1,[1]bd_mala_direta!$A$1:$A$3048,[1]bd_mala_direta!$E$1:$E$3048,"-",0,-1),IF(D3="informacao",_xlfn.XLOOKUP(D1,[1]bd_mala_direta!$A$1:$A$3048,[1]bd_mala_direta!$G$1:$G$3048,"-",0,-1),"Erro"))) -> A Meta TJMG 7, que exige a publicação de 95% dos acórdãos em até 10 dias após o julgamento, o valor médio alcançado foi de 92% até outubro de 2025. O CEINJUR explica que não alcance da meta foi resultado de erros estruturais que afetaram os dados de janeiro e início de fevereiro. Esses problemas foram resolvidos no final de fevereiro, permitindo a normalização dos indicadores. Além disso, o mês de dezembro é atípico por conta do recesso judiciário, o que também impacta os resultados de início de ano. No entanto, a tendência dos resultados aponta para o alcance da meta até o final do ano. | E2: =IF(E3="data",_xlfn.XLOOKUP(E1,[1]bd_mala_direta!$A$1:$A$3048,[1]bd_mala_direta!$D$1:$D$3048,"-",0,-1),IF(E3="valor",_xlfn.XLOOKUP(E1,[1]bd_mala_direta!$A$1:$A$3048,[1]bd_mala_direta!$E$1:$E$3048,"-",0,-1),IF(E3="informacao",_xlfn.XLOOKUP(E1,[1]bd_mala_direta!$A$1:$A$3048,[1]bd_mala_direta!$G$1:$G$3048,"-",0,-1),"Erro"))) -> 45838 | F2: =IF(F3="data",_xlfn.XLOOKUP(F1,[1]bd_mala_direta!$A$1:$A$3048,[1]bd_mala_direta!$D$1:$D$3048,"-",0,-1),IF(F3="valor",_xlfn.XLOOKUP(F1,[1]bd_mala_direta!$A$1:$A$3048,[1]bd_mala_direta!$E$1:$E$3048,"-",0,-1),IF(F3="informacao",_xlfn.XLOOKUP(F1,[1]bd_mala_direta!$A$1:$A$3048,[1]bd_mala_direta!$G$1:$G$3048,"-",0,-1),"Erro"))) -> 40.02 | G2: =IF(G3="data",_xlfn.XLOOKUP(G1,[1]bd_mala_direta!$A$1:$A$3048,[1]bd_mala_direta!$D$1:$D$3048,"-",0,-1),IF(G3="valor",_xlfn.XLOOKUP(G1,[1]bd_mala_direta!$A$1:$A$3048,[1]bd_mala_direta!$E$1:$E$3048,"-",0,-1),IF(G3="informacao",_xlfn.XLOOKUP(G1,[1]bd_mala_direta!$A$1:$A$3048,[1]bd_mala_direta!$G$1:$G$3048,"-",0,-1),"Erro"))) -> Em junho de 2025, apurou-se um montante de 33.806 mandados judiciais em atraso na Primeira Instância há mais de 30 (trinta) dias, o que corresponde a uma redução de 40,02% dos mandados judiciais em atraso em relação a dezembro de 2024 (56.524 mandados em atraso). É esperada uma redução de, pelo menos, 12% no ano. Embora a meta tenha sido alcançada no 1º semestre, é necessário manter o bom resultado até o final do ano. Visando o alcance da meta, a Gerência de Mandados (GEMAN) promoveu cooperações entre oficiais de justiça em comarcas que possuíam maior número de mandados judicias em atraso ou maior volume de mandados judiciais a serem cumpridos. No 1º semestre deste ano, ocorreram cooperações em: Paraguaçu, Itabirito, Sabará, Mariana e Águas Formosas. Não há previsão de cooperação para o 2º semestre, tendo em vista que está em análise a viabilidade de implantação de um projeto de cooperação permanente, em parceria com o sindicato (Sindojus). Adicionalmente, está sendo avaliada a possibilidade de envio de lembretes automáticos para as Centrais de Mandados, a partir do Painel de Mandados Distribuídos e Redistribuídos, sempre que, por exemplo, os mandados estiverem próximos ao vencimento ou atrasados. Além disso, foi instituído o projeto piloto “Cooperação de Oficiais de Justiça na Busca e Restrições de Bens – CBRB”. De acordo com a Portaria conjunta 1664/PR/2025, que institui o projeto piloto, a cooperação será destinada à realização das atividades afetas à busca, à pesquisa e à restrição de bens por oficiais de justiça lotados na Comarca de Belo Horizonte em cooperação com a Central de Cumprimento de Sentença Cível – CENTRASE, contemplando, inclusive, os processos que estiverem remetidos à Central de Pesquisa Patrimonial - CPP. | H2: =IF(H3="data",_xlfn.XLOOKUP(H1,[1]bd_mala_direta!$A$1:$A$3048,[1]bd_mala_direta!$D$1:$D$3048,"-",0,-1),IF(H3="valor",_xlfn.XLOOKUP(H1,[1]bd_mala_direta!$A$1:$A$3048,[1]bd_mala_direta!$E$1:$E$3048,"-",0,-1),IF(H3="informacao",_xlfn.XLOOKUP(H1,[1]bd_mala_direta!$A$1:$A$3048,[1]bd_mala_direta!$G$1:$G$3048,"-",0,-1),"Erro"))) -> 45905 | I2: =IF(I3="data",_xlfn.XLOOKUP(I1,[1]bd_mala_direta!$A$1:$A$3048,[1]bd_mala_direta!$D$1:$D$3048,"-",0,-1),IF(I3="valor",_xlfn.XLOOKUP(I1,[1]bd_mala_direta!$A$1:$A$3048,[1]bd_mala_direta!$E$1:$E$3048,"-",0,-1),IF(I3="informacao",_xlfn.XLOOKUP(I1,[1]bd_mala_direta!$A$1:$A$3048,[1]bd_mala_direta!$G$1:$G$3048,"-",0,-1),"Erro"))) -> 63 | ... EO2: =IF(EO3="data",_xlfn.XLOOKUP(EO1,[1]bd_mala_direta!$A$1:$A$3048,[1]bd_mala_direta!$D$1:$D$3048,"-",0,-1),IF(EO3="valor",_xlfn.XLOOKUP(EO1,[1]bd_mala_direta!$A$1:$A$3048,[1]bd_mala_direta!$E$1:$E$3048,"-",0,-1),IF(EO3="informacao",_xlfn.XLOOKUP(EO1,[1]bd_mala_direta!$A$1:$A$3048,[1]bd_mala_direta!$G$1:$G$3048,"-",0,-1),"Erro"))) -> Em junho de 2025, apurou-se um montante de 5.498 processos que possuem réu falecido, o que corresponde a um aumento de 36,3% dos feitos em relação a dezembro de 2024 (4.035 processos). É esperada uma redução de, pelo menos, 50% no ano. Anualmente, o Tribunal de Justiça de Minas Gerais (TJMG) solicita ao Tribunal Regional Eleitoral (TRE) a listagem de pessoas falecidas no período, para que seja avaliada a possibilidade de baixar os processos judiciais com falecimento do imputado como autor do fato (réus falecidos). A partir do recebimento da listagem do TRE, é esperado um aumento imediato no quantitativo de processos, mas, considerando a previsão de realização do esforço concentrado para baixa desses processos, pelas unidades judiciárias, entre outubro e novembro deste ano, estima-se que a meta seja alcançada. Destaca-se, ainda, que está sendo desenvolvido um robô que automatizará a identificação da certidão de óbito do réu falecido e o Cartório de Registro Civil (CRC) em que foi registrada, desonerando o juiz dessa atividade e otimizando os trâmites necessários ao encerramento do processo.
A3: tipo | B3: data | C3: valor | D3: informacao | E3: data | F3: valor | G3: informacao | H3: data | I3: valor | J3: informacao | K3: data | L3: valor | M3: informacao | N3: data | O3: valor | P3: informacao | Q3: data | R3: valor | S3: informacao | T3: data | U3: valor | V3: informacao | W3: data | X3: valor | Y3: informacao | Z3: data | AA3: valor | AB3: informacao | AC3: data | AD3: valor | AE3: informacao | AF3: data | AG3: valor | AH3: informacao | AI3: data | AJ3: valor | AK3: informacao | AL3: data | AM3: valor | AN3: informacao | AO3: data | AP3: valor | AQ3: informacao | AR3: data | AS3: valor | AT3: informacao | AU3: data | AV3: valor | AW3: informacao | AX3: data | AY3: valor | AZ3: informacao | BA3: data | BB3: valor | BC3: informacao | BD3: data | BE3: valor | BF3: informacao | BG3: data | BH3: valor | BI3: informacao | BJ3: data | BK3: valor | BL3: informacao | BM3: data | BN3: valor | BO3: informacao | BP3: data | BQ3: valor | BR3: informacao | BS3: data | BT3: valor | BU3: informacao | BV3: data | BW3: valor | BX3: informacao | BY3: data | BZ3: valor | CA3: informacao | CB3: data | CC3: valor | CD3: informacao | CE3: data | CF3: valor | CG3: informacao | CH3: data | CI3: valor | CJ3: informacao | CK3: data | CL3: valor | CM3: informacao | CN3: data | CO3: valor | CP3: informacao | CQ3: data | CR3: valor | CS3: informacao | CT3: data | CU3: valor | CV3: informacao | CW3: data | CX3: valor | CY3: informacao | CZ3: data | DA3: valor | DB3: informacao | DC3: data | DD3: valor | DE3: informacao | DF3: data | DG3: valor | DH3: informacao | DI3: data | DJ3: valor | DK3: informacao | DL3: data | DM3: valor | DN3: informacao | DO3: data | DP3: valor | DQ3: informacao | DR3: data | DS3: valor | DT3: informacao | DU3: data | DV3: valor | DW3: informacao | DX3: data | DY3: valor | DZ3: informacao | EA3: data | EB3: valor | EC3: informacao | ED3: data | EE3: valor | EF3: informacao | EG3: data | EH3: valor | EI3: informacao | EJ3: data | EK3: valor | EL3: informacao | EM3: data | EN3: valor | EO3: informacao

Sheet procv
A1: meta | B1: TJMG 7 - | C1: TJMG 7 - | D1: TJMG 7 - | E1: TJMG 10 | F1: TJMG 10 | G1: TJMG 10 | H1: TJMG 100 | I1: TJMG 100 | J1: TJMG 100 | K1: TJMG 102 | L1: TJMG 102 | M1: TJMG 102 | N1: TJMG 104 | O1: TJMG 104 | P1: TJMG 104 | Q1: TJMG 105 | R1: TJMG 105 | S1: TJMG 105 | T1: TJMG 106 | U1: TJMG 106 | V1: TJMG 106 | W1: TJMG 107 | X1: TJMG 107 | Y1: TJMG 107 | Z1: TJMG 108 | AA1: TJMG 108 | AB1: TJMG 108 | AC1: TJMG 109 | AD1: TJMG 109 | AE1: TJMG 109 | AF1: TJMG 11 | AG1: TJMG 11 | AH1: TJMG 11 | AI1: TJMG 110 | AJ1: TJMG 110 | AK1: TJMG 110 | AL1: TJMG 111 | AM1: TJMG 111 | AN1: TJMG 111 | AO1: TJMG 112 | AP1: TJMG 112 | AQ1: TJMG 112 | AR1: TJMG 113 | AS1: TJMG 113 | AT1: TJMG 113 | AU1: TJMG 114 | AV1: TJMG 114 | AW1: TJMG 114 | AX1: TJMG 115 | AY1: TJMG 115 | AZ1: TJMG 115 | BA1: TJMG 116 | BB1: TJMG 116 | BC1: TJMG 116 | BD1: TJMG 117 | BE1: TJMG 117 | BF1: TJMG 117 | BG1: TJMG 118 | BH1: TJMG 118 | BI1: TJMG 118 | BJ1: TJMG 119 | BK1: TJMG 119 | BL1: TJMG 119 | BM1: TJMG 12 | BN1: TJMG 12 | BO1: TJMG 12 | BP1: TJMG 120 | BQ1: TJMG 120 | BR1: TJMG 120 | BS1: TJMG 121 | BT1: TJMG 121 | BU1: TJMG 121 | BV1: TJMG 122 | BW1: TJMG 122 | BX1: TJMG 122 | BY1: TJMG 123 | BZ1: TJMG 123 | CA1: TJMG 123 | CB1: TJMG 124 | CC1: TJMG 124 | CD1: TJMG 124 | CE1: TJMG 125 | CF1: TJMG 125 | CG1: TJMG 125 | CH1: TJMG 126 | CI1: TJMG 126 | CJ1: TJMG 126 | CK1: TJMG 127 | CL1: TJMG 127 | CM1: TJMG 127 | CN1: TJMG 13 | CO1: TJMG 13 | CP1: TJMG 13 | CQ1: TJMG 17 | CR1: TJMG 17 | CS1: TJMG 17 | CT1: TJMG 1a | CU1: TJMG 1a | CV1: TJMG 1a | CW1: TJMG 1d | CX1: TJMG 1d | CY1: TJMG 1d | CZ1: TJMG 1f | DA1: TJMG 1f | DB1: TJMG 1f | DC1: TJMG 1g | DD1: TJMG 1g | DE1: TJMG 1g | DF1: TJMG 23 | DG1: TJMG 23 | DH1: TJMG 23 | DI1: TJMG 27 | DJ1: TJMG 27 | DK1: TJMG 27 | DL1: TJMG 29 | DM1: TJMG 29 | DN1: TJMG 29 | DO1: TJMG 31 | DP1: TJMG 31 | DQ1: TJMG 31 | DR1: TJMG 32 | DS1: TJMG 32 | DT1: TJMG 32 | DU1: TJMG 40 | DV1: TJMG 40 | DW1: TJMG 40 | DX1: TJMG 42 | DY1: TJMG 42 | DZ1: TJMG 42 | EA1: TJMG 44 | EB1: TJMG 44 | EC1: TJMG 44 | ED1: TJMG 46 | EE1: TJMG 46 | EF1: TJMG 46 | EG1: TJMG 48 | EH1: TJMG 48 | EI1: TJMG 48 | EJ1: TJMG 5 - | EK1: TJMG 5 - | EL1: TJMG 5 - | EM1: TJMG 54 | EN1: TJMG 54 | EO1: TJMG 54 | EP1: TJMG 59 | EQ1: TJMG 59 | ER1: TJMG 59 | ES1: TJMG 6 - | ET1: TJMG 6 - | EU1: TJMG 6 - | EV1: TJMG 62 | EW1: TJMG 62 | EX1: TJMG 62 | EY1: TJMG 64 | EZ1: TJMG 64 | FA1: TJMG 64 | FB1: TJMG 66 | FC1: TJMG 66 | FD1: TJMG 66 | FE1: TJMG 67 | FF1: TJMG 67 | FG1: TJMG 67 | FH1: TJMG 68 | FI1: TJMG 68 | FJ1: TJMG 68 | FK1: TJMG 69 | FL1: TJMG 69 | FM1: TJMG 69 | FN1: TJMG 7 - | FO1: TJMG 7 - | FP1: TJMG 7 - | FQ1: TJMG 77 | FR1: TJMG 77 | FS1: TJMG 77 | FT1: TJMG 78 | FU1: TJMG 78 | FV1: TJMG 78 | FW1: TJMG 79 | FX1: TJMG 79 | FY1: TJMG 79 | FZ1: TJMG 8 - | GA1: TJMG 8 - | GB1: TJMG 8 - | GC1: TJMG 80 | GD1: TJMG 80 | GE1: TJMG 80 | GF1: TJMG 84 | GG1: TJMG 84 | GH1: TJMG 84 | GI1: TJMG 85 | GJ1: TJMG 85 | GK1: TJMG 85 | GL1: TJMG 87 | GM1: TJMG 87 | GN1: TJMG 87 | GO1: TJMG 88 | GP1: TJMG 88 | GQ1: TJMG 88 | GR1: TJMG 89 | GS1: TJMG 89 | GT1: TJMG 89 | GU1: TJMG 9 - | GV1: TJMG 9 - | GW1: TJMG 9 - | GX1: TJMG 90 | GY1: TJMG 90 | GZ1: TJMG 90 | HA1: TJMG 91 | HB1: TJMG 91 | HC1: TJMG 91 | HD1: TJMG 93 | HE1: TJMG 93 | HF1: TJMG 93 | HG1: TJMG 94 | HH1: TJMG 94 | HI1: TJMG 94 | HJ1: TJMG 95 | HK1: TJMG 95 | HL1: TJMG 95 | HM1: TJMG 96 | HN1: TJMG 96 | HO1: TJMG 96 | HP1: TJMG 97 | HQ1: TJMG 97 | HR1: TJMG 97 | HS1: TJMG 98 | HT1: TJMG 98 | HU1: TJMG 98 | HV1: TJMG 99 | HW1: TJMG 99 | HX1: TJMG 99 | HY1: TJMG 128 | HZ1: TJMG 128 | IA1: TJMG 128 | IB1: TJMG 129 | IC1: TJMG 129 | ID1: TJMG 129 | IE1: TJMG 130 | IF1: TJMG 130 | IG1: TJMG 130 | IH1: TJMG 131 | II1: TJMG 131 | IJ1: TJMG 131 | IK1: TJMG 132 | IL1: TJMG 132 | IM1: TJMG 132 | IN1: TJMG 133 | IO1: TJMG 133 | IP1: TJMG 133 | IQ1: TJMG 134 | IR1: TJMG 134 | IS1: TJMG 134 | IT1: TJMG 135 | IU1: TJMG 135 | IV1: TJMG 135 | IW1: TJMG 136 | IX1: TJMG 136 | IY1: TJMG 136 | IZ1: TJMG 137 | JA1: TJMG 137 | JB1: TJMG 137 | JC1: TJMG 138 | JD1: TJMG 138 | JE1: TJMG 138 | JF1: TJMG 139 | JG1: TJMG 139 | JH1: TJMG 139 | JI1: TJMG 140 | JJ1: TJMG 140 | JK1: TJMG 140 | JL1: TJMG 141 | JM1: TJMG 141 | JN1: TJMG 141 | JO1: TJMG 142 | JP1: TJMG 142 | JQ1: TJMG 142 | JR1: TJMG 143 | JS1: TJMG 143 | JT1: TJMG 143 | JU1: TJMG 144 | JV1: TJMG 144 | JW1: TJMG 144 | JX1: TJMG 145 | JY1: TJMG 145 | JZ1: TJMG 145 | KA1: TJMG 146 | KB1: TJMG 146 | KC1: TJMG 146 | KD1: TJMG 147 | KE1: TJMG 147 | KF1: TJMG 147 | KG1: TJMG 148 | KH1: TJMG 148 | KI1: TJMG 148 | KJ1: TJMG 149 | KK1: TJMG 149 | KL1: TJMG 149
A2: dezembro | B2: 12 | C2: 12 | D2: 12 | E2: 12 | F2: 12 | G2: 12 | H2: 12 | I2: 12 | J2: 12 | K2: 12 | L2: 12 | M2: 12 | N2: 12 | O2: 12 | P2: 12 | Q2: 12 | R2: 12 | S2: 12 | T2: 12 | U2: 12 | V2: 12 | W2: 12 | X2: 12 | Y2: 12 | Z2: 12 | AA2: 12 | AB2: 12 | AC2: 12 | AD2: 12 | AE2: 12 | AF2: 12 | AG2: 12 | AH2: 12 | AI2: 12 | AJ2: 12 | AK2: 12 | AL2: 12 | AM2: 12 | AN2: 12 | AO2: 12 | AP2: 12 | AQ2: 12 | AR2: 12 | AS2: 12 | AT2: 12 | AU2: 12 | AV2: 12 | AW2: 12 | AX2: 12 | AY2: 12 | AZ2: 12 | BA2: 12 | BB2: 12 | BC2: 12 | BD2: 12 | BE2: 12 | BF2: 12 | BG2: 12 | BH2: 12 | BI2: 12 | BJ2: 12 | BK2: 12 | BL2: 12 | BM2: 12 | BN2: 12 | BO2: 12 | BP2: 12 | BQ2: 12 | BR2: 12 | BS2: 12 | BT2: 12 | BU2: 12 | BV2: 12 | BW2: 12 | BX2: 12 | BY2: 12 | BZ2: 12 | CA2: 12 | CB2: 12 | CC2: 12 | CD2: 12 | CE2: 12 | CF2: 12 | CG2: 12 | CH2: 12 | CI2: 12 | CJ2: 12 | CK2: 12 | CL2: 12 | CM2: 12 | CN2: 12 | CO2: 12 | CP2: 12 | CQ2: 12 | CR2: 12 | CS2: 12 | CT2: 12 | CU2: 12 | CV2: 12 | CW2: 12 | CX2: 12 | CY2: 12 | CZ2: 12 | DA2: 12 | DB2: 12 | DC2: 12 | DD2: 12 | DE2: 12 | DF2: 12 | DG2: 12 | DH2: 12 | DI2: 12 | DJ2: 12 | DK2: 12 | DL2: 12 | DM2: 12 | DN2: 12 | DO2: 12 | DP2: 12 | DQ2: 12 | DR2: 12 | DS2: 12 | DT2: 12 | DU2: 12 | DV2: 12 | DW2: 12 | DX2: 12 | DY2: 12 | DZ2: 12 | EA2: 12 | EB2: 12 | EC2: 12 | ED2: 12 | EE2: 12 | EF2: 12 | EG2: 12 | EH2: 12 | EI2: 12 | EJ2: 12 | EK2: 12 | EL2: 12 | EM2: 12 | EN2: 12 | EO2: 12 | EP2: 12 | EQ2: 12 | ER2: 12 | ES2: 12 | ET2: 12 | EU2: 12 | EV2: 12 | EW2: 12 | EX2: 12 | EY2: 12 | EZ2: 12 | FA2: 12 | FB2: 12 | FC2: 12 | FD2: 12 | FE2: 12 | FF2: 12 | FG2: 12 | FH2: 12 | FI2: 12 | FJ2: 12 | FK2: 12 | FL2: 12 | FM2: 12 | FN2: 12 | FO2: 12 | FP2: 12 | FQ2: 12 | FR2: 12 | FS2: 12 | FT2: 12 | FU2: 12 | FV2: 12 | FW2: 12 | FX2: 12 | FY2: 12 | FZ2: 12 | GA2: 12 | GB2: 12 | GC2: 12 | GD2: 12 | GE2: 12 | GF2: 12 | GG2: 12 | GH2: 12 | GI2: 12 | GJ2: 12 | GK2: 12 | GL2: 12 | GM2: 12 | GN2: 12 | GO2: 12 | GP2: 12 | GQ2: 12 | GR2: 12 | GS2: 12 | GT2: 12 | GU2: 12 | GV2: 12 | GW2: 12 | GX2: 12 | GY2: 12 | GZ2: 12 | HA2: 12 | HB2: 12 | HC2: 12 | HD2: 12 | HE2: 12 | HF2: 12 | HG2: 12 | HH2: 12 | HI2: 12 | HJ2: 12 | HK2: 12 | HL2: 12 | HM2: 12 | HN2: 12 | HO2: 12 | HP2: 12 | HQ2: 12 | HR2: 12 | HS2: 12 | HT2: 12 | HU2: 12 | HV2: 12 | HW2: 12 | HX2: 12 | HY2: 12 | HZ2: 12 | IA2: 12 | IB2: 12 | IC2: 12 | ID2: 12 | IE2: 12 | IF2: 12 | IG2: 12 | IH2: 12 | II2: 12 | IJ2: 12 | IK2: 12 | IL2: 12 | IM2: 12 | IN2: 12 | IO2: 12 | IP2: 12 | IQ2: 12 | IR2: 12 | IS2: 12 | IT2: 12 | IU2: 12 | IV2: 12 | IW2: 12 | IX2: 12 | IY2: 12 | IZ2: 12 | JA2: 12 | JB2: 12 | JC2: 12 | JD2: 12 | JE2: 12 | JF2: 12 | JG2: 12 | JH2: 12 | JI2: 12 | JJ2: 12 | JK2: 12 | JL2: 12 | JM2: 12 | JN2: 12 | JO2: 12 | JP2: 12 | JQ2: 12 | JR2: 12 | JS2: 12 | JT2: 12 | JU2: 12 | JV2: 12 | JW2: 12 | JX2: 12 | JY2: 12 | JZ2: 12 | KA2: 12 | KB2: 12 | KC2: 12 | KD2: 12 | KE2: 12 | KF2: 12 | KG2: 12 | KH2: 12 | KI2: 12 | KJ2: 12 | KK2: 12 | KL2: 12
A3: periodo | B3: Apurado no período | C3: Apurado no período | D3: Apurado no período | E3: Apurado no período | F3: Apurado no período | G3: Apurado no período | H3: Apurado no período | I3: Apurado no período | J3: Apurado no período | K3: Apurado no período | L3: Apurado no período | M3: Apurado no período | N3: Apurado no período | O3: Apurado no período | P3: Apurado no período | Q3: Apurado no período | R3: Apurado no período | S3: Apurado no período | T3: Apurado no período | U3: Apurado no período | V3: Apurado no período | W3: Apurado no período | X3: Apurado no período | Y3: Apurado no período | Z3: Apurado no período | AA3: Apurado no período | AB3: Apurado no período | AC3: Apurado no período | AD3: Apurado no período | AE3: Apurado no período | AF3: Apurado no período | AG3: Apurado no período | AH3: Apurado no período | AI3: Apurado no período | AJ3: Apurado no período | AK3: Apurado no período | AL3: Apurado no período | AM3: Apurado no período | AN3: Apurado no período | AO3: Apurado no período | AP3: Apurado no período | AQ3: Apurado no período | AR3: Apurado no período | AS3: Apurado no período | AT3: Apurado no período | AU3: Apurado no período | AV3: Apurado no período | AW3: Apurado no período | AX3: Apurado no período | AY3: Apurado no período | AZ3: Apurado no período | BA3: Apurado no período | BB3: Apurado no período | BC3: Apurado no período | BD3: Apurado no período | BE3: Apurado no período | BF3: Apurado no período | BG3: Apurado no período | BH3: Apurado no período | BI3: Apurado no período | BJ3: Apurado no período | BK3: Apurado no período | BL3: Apurado no período | BM3: Apurado no período | BN3: Apurado no período | BO3: Apurado no período | BP3: Apurado no período | BQ3: Apurado no período | BR3: Apurado no período | BS3: Apurado no período | BT3: Apurado no período | BU3: Apurado no período | BV3: Apurado no período | BW3: Apurado no período | BX3: Apurado no período | BY3: Apurado no período | BZ3: Apurado no período | CA3: Apurado no período | CB3: Apurado no período | CC3: Apurado no período | CD3: Apurado no período | CE3: Apurado no período | CF3: Apurado no período | CG3: Apurado no período | CH3: Apurado no período | CI3: Apurado no período | CJ3: Apurado no período | CK3: Apurado no período | CL3: Apurado no período | CM3: Apurado no período | CN3: Apurado no período | CO3: Apurado no período | CP3: Apurado no período | CQ3: Apurado no período | CR3: Apurado no período | CS3: Apurado no período | CT3: Apurado no período | CU3: Apurado no período | CV3: Apurado no período | CW3: Apurado no período | CX3: Apurado no período | CY3: Apurado no período | CZ3: Apurado no período | DA3: Apurado no período | DB3: Apurado no período | DC3: Apurado no período | DD3: Apurado no período | DE3: Apurado no período | DF3: Apurado no período | DG3: Apurado no período | DH3: Apurado no período | DI3: Apurado no período | DJ3: Apurado no período | DK3: Apurado no período | DL3: Apurado no período | DM3: Apurado no período | DN3: Apurado no período | DO3: Apurado no período | DP3: Apurado no período | DQ3: Apurado no período | DR3: Apurado no período | DS3: Apurado no período | DT3: Apurado no período | DU3: Apurado no período | DV3: Apurado no período | DW3: Apurado no período | DX3: Apurado no período | DY3: Apurado no período | DZ3: Apurado no período | EA3: Apurado no período | EB3: Apurado no período | EC3: Apurado no período | ED3: Apurado no período | EE3: Apurado no período | EF3: Apurado no período | EG3: Apurado no período | EH3: Apurado no período | EI3: Apurado no período | EJ3: Apurado no período | EK3: Apurado no período | EL3: Apurado no período | EM3: Apurado no período | EN3: Apurado no período | EO3: Apurado no período | EP3: Apurado no período | EQ3: Apurado no período | ER3: Apurado no período | ES3: Apurado no período | ET3: Apurado no período | EU3: Apurado no período | EV3: Apurado no período | EW3: Apurado no período | EX3: Apurado no período | EY3: Apurado no período | EZ3: Apurado no período | FA3: Apurado no período | FB3: Apurado no período | FC3: Apurado no período | FD3: Apurado no período | FE3: Apurado no período | FF3: Apurado no período | FG3: Apurado no período | FH3: Apurado no período | FI3: Apurado no período | FJ3: Apurado no período | FK3: Apurado no período | FL3: Apurado no período | FM3: Apurado no período | FN3: Apurado no período | FO3: Apurado no período | FP3: Apurado no período | FQ3: Apurado no período | FR3: Apurado no período | FS3: Apurado no período | FT3: Apurado no período | FU3: Apurado no período | FV3: Apurado no período | FW3: Apurado no período | FX3: Apurado no período | FY3: Apurado no período | FZ3: Apurado no período | GA3: Apurado no período | GB3: Apurado no período | GC3: Apurado no período | GD3: Apurado no período | GE3: Apurado no período | GF3: Apurado no período | GG3: Apurado no período | GH3: Apurado no período | GI3: Apurado no período | GJ3: Apurado no período | GK3: Apurado no período | GL3: Apurado no período | GM3: Apurado no período | GN3: Apurado no período | GO3: Apurado no período | GP3: Apurado no período | GQ3: Apurado no período | GR3: Apurado no período | GS3: Apurado no período | GT3: Apurado no período | GU3: Apurado no período | GV3: Apurado no período | GW3: Apurado no período | GX3: Apurado no período | GY3: Apurado no período | GZ3: Apurado no período | HA3: Apurado no período | HB3: Apurado no período | HC3: Apurado no período | HD3: Apurado no período | HE3: Apurado no período | HF3: Apurado no período | HG3: Apurado no período | HH3: Apurado no período | HI3: Apurado no período | HJ3: Apurado no período | HK3: Apurado no período | HL3: Apurado no período | HM3: Apurado no período | HN3: Apurado no período | HO3: Apurado no período | HP3: Apurado no período | HQ3: Apurado no período | HR3: Apurado no período | HS3: Apurado no período | HT3: Apurado no período | HU3: Apurado no período | HV3: Apurado no período | HW3: Apurado no período | HX3: Apurado no período | HY3: Apurado no período | HZ3: Apurado no período | IA3: Apurado no período | IB3: Apurado no período | IC3: Apurado no período | ID3: Apurado no período | IE3: Apurado no período | IF3: Apurado no período | IG3: Apurado no período | IH3: Apurado no período | II3: Apurado no período | IJ3: Apurado no período | IK3: Apurado no período | IL3: Apurado no período | IM3: Apurado no período | IN3: Apurado no período | IO3: Apurado no período | IP3: Apurado no período | IQ3: Apurado no período | IR3: Apurado no período | IS3: Apurado no período | IT3: Apurado no período | IU3: Apurado no período | IV3: Apurado no período | IW3: Apurado no período | IX3: Apurado no período | IY3: Apurado no período | IZ3: Apurado no período | JA3: Apurado no período | JB3: Apurado no período | JC3: Apurado no período | JD3: Apurado no período | JE3: Apurado no período | JF3: Apurado no período | JG3: Apurado no período | JH3: Apurado no período | JI3: Apurado no período | JJ3: Apurado no período | JK3: Apurado no período | JL3: Apurado no período | JM3: Apurado no período | JN3: Apurado no período | JO3: Apurado no período | JP3: Apurado no período | JQ3: Apurado no período | JR3: Apurado no período | JS3: Apurado no período | JT3: Apurado no período | JU3: Apurado no período | JV3: Apurado no período | JW3: Apurado no período | JX3: Apurado no período | JY3: Apurado no período | JZ3: Apurado no período | KA3: Apurado no período | KB3: Apurado no período | KC3: Apurado no período | KD3: Apurado no período | KE3: Apurado no período | KF3: Apurado no período | KG3: Apurado no período | KH3: Apurado no período | KI3: Apurado no período | KJ3: Apurado no período | KK3: Apurado no período | KL3: Apurado no período
